mlstac/__init__.py
mlstac/_quiet.py
mlstac/fetch.py
mlstac/main.py
mlstac/utils.py
mlstac-0.4.5.dist-info/LICENSE
mlstac-0.4.5.dist-info/METADATA
mlstac-0.4.5.dist-info/WHEEL
mlstac-0.4.5.dist-info/RECORD
