Metadata-Version: 2.1
Name: mlstac
Version: 0.4.5
Summary: A machine learning model-sharing specification based on STAC MLM and Safetensors.
Home-page: https://github.com/csaybar/isp-models
Author: Cesar Aybar
Author-email: cesar.aybar@uv.es
Requires-Python: >=3.10,<4.0
Classifier: Programming Language :: Python :: 3
Classifier: Programming Language :: Python :: 3.10
Classifier: Programming Language :: Python :: 3.11
Classifier: Programming Language :: Python :: 3.12
Requires-Dist: fsspec (>=2024.10.0)
Requires-Dist: pystac (>=1.12.2)
Requires-Dist: safetensors (>=0.5.2)
Requires-Dist: tqdm (>=4.67.1)
Project-URL: Documentation, https://csaybar.github.io/isp-models/
Project-URL: Repository, https://github.com/csaybar/isp-models
